gp/__init__.py
gp/core.py
gp/data.py
gp/modules.py
genepattern_python-24.1.dist-info/LICENSE.txt
genepattern_python-24.1.dist-info/METADATA
genepattern_python-24.1.dist-info/WHEEL
genepattern_python-24.1.dist-info/top_level.txt
genepattern_python-24.1.dist-info/RECORD
