Metadata-Version: 2.1
Name: genepattern-python
Version: 24.1
Summary: Library for programmatically interacting with GenePattern from Python.
Home-page: https://github.com/genepattern/genepattern-python
Download-URL: https://github.com/genepattern/genepattern-python/archive/24.01.tar.gz
Author: Thorin Tabor
Author-email: tmtabor@cloud.ucsd.edu
License: BSD
Keywords: genepattern,genomics,bioinformatics
License-File: LICENSE.txt
